[
  {
    "section": "ela",
    "category": "ela.revising.grammar.clarity_concision",
    "difficulty": 1,
    "type": "multiple_choice",
    "stem": "Practice question 1 for clarity concision",
    "options": [
      {
        "label": "A",
        "text": "Option A"
      },
      {
        "label": "B",
        "text": "Option B"
      },
      {
        "label": "C",
        "text": "Option C"
      },
      {
        "label": "D",
        "text": "Option D"
      }
    ],
    "correctAnswer": "A",
    "explanation": "Detailed explanation for ela.revising.grammar.clarity_concision",
    "commonMistakes": [
      {
        "label": "Common error",
        "explanation": "Students often make this type of mistake."
      },
      {
        "label": "Another mistake",
        "explanation": "This is another frequent error."
      }
    ],
    "skills": [
      "clarity_concision"
    ],
    "tags": [
      "ela",
      "practice"
    ]
  },
  {
    "section": "ela",
    "category": "ela.revising.grammar.clarity_concision",
    "difficulty": 2,
    "type": "multiple_choice",
    "stem": "Practice question 2 for clarity concision",
    "options": [
      {
        "label": "A",
        "text": "Option A"
      },
      {
        "label": "B",
        "text": "Option B"
      },
      {
        "label": "C",
        "text": "Option C"
      },
      {
        "label": "D",
        "text": "Option D"
      }
    ],
    "correctAnswer": "A",
    "explanation": "Detailed explanation for ela.revising.grammar.clarity_concision",
    "commonMistakes": [
      {
        "label": "Common error",
        "explanation": "Students often make this type of mistake."
      },
      {
        "label": "Another mistake",
        "explanation": "This is another frequent error."
      }
    ],
    "skills": [
      "clarity_concision"
    ],
    "tags": [
      "ela",
      "practice"
    ]
  },
  {
    "section": "ela",
    "category": "ela.revising.grammar.clarity_concision",
    "difficulty": 3,
    "type": "multiple_choice",
    "stem": "Practice question 3 for clarity concision",
    "options": [
      {
        "label": "A",
        "text": "Option A"
      },
      {
        "label": "B",
        "text": "Option B"
      },
      {
        "label": "C",
        "text": "Option C"
      },
      {
        "label": "D",
        "text": "Option D"
      }
    ],
    "correctAnswer": "A",
    "explanation": "Detailed explanation for ela.revising.grammar.clarity_concision",
    "commonMistakes": [
      {
        "label": "Common error",
        "explanation": "Students often make this type of mistake."
      },
      {
        "label": "Another mistake",
        "explanation": "This is another frequent error."
      }
    ],
    "skills": [
      "clarity_concision"
    ],
    "tags": [
      "ela",
      "practice"
    ]
  },
  {
    "section": "ela",
    "category": "ela.revising.grammar.clarity_concision",
    "difficulty": 4,
    "type": "multiple_choice",
    "stem": "Practice question 4 for clarity concision",
    "options": [
      {
        "label": "A",
        "text": "Option A"
      },
      {
        "label": "B",
        "text": "Option B"
      },
      {
        "label": "C",
        "text": "Option C"
      },
      {
        "label": "D",
        "text": "Option D"
      }
    ],
    "correctAnswer": "A",
    "explanation": "Detailed explanation for ela.revising.grammar.clarity_concision",
    "commonMistakes": [
      {
        "label": "Common error",
        "explanation": "Students often make this type of mistake."
      },
      {
        "label": "Another mistake",
        "explanation": "This is another frequent error."
      }
    ],
    "skills": [
      "clarity_concision"
    ],
    "tags": [
      "ela",
      "practice"
    ]
  },
  {
    "section": "ela",
    "category": "ela.revising.grammar.clarity_concision",
    "difficulty": 5,
    "type": "multiple_choice",
    "stem": "Practice question 5 for clarity concision",
    "options": [
      {
        "label": "A",
        "text": "Option A"
      },
      {
        "label": "B",
        "text": "Option B"
      },
      {
        "label": "C",
        "text": "Option C"
      },
      {
        "label": "D",
        "text": "Option D"
      }
    ],
    "correctAnswer": "A",
    "explanation": "Detailed explanation for ela.revising.grammar.clarity_concision",
    "commonMistakes": [
      {
        "label": "Common error",
        "explanation": "Students often make this type of mistake."
      },
      {
        "label": "Another mistake",
        "explanation": "This is another frequent error."
      }
    ],
    "skills": [
      "clarity_concision"
    ],
    "tags": [
      "ela",
      "practice"
    ]
  },
  {
    "section": "ela",
    "category": "ela.revising.grammar.clarity_concision",
    "difficulty": 1,
    "type": "multiple_choice",
    "stem": "Practice question 6 for clarity concision",
    "options": [
      {
        "label": "A",
        "text": "Option A"
      },
      {
        "label": "B",
        "text": "Option B"
      },
      {
        "label": "C",
        "text": "Option C"
      },
      {
        "label": "D",
        "text": "Option D"
      }
    ],
    "correctAnswer": "A",
    "explanation": "Detailed explanation for ela.revising.grammar.clarity_concision",
    "commonMistakes": [
      {
        "label": "Common error",
        "explanation": "Students often make this type of mistake."
      },
      {
        "label": "Another mistake",
        "explanation": "This is another frequent error."
      }
    ],
    "skills": [
      "clarity_concision"
    ],
    "tags": [
      "ela",
      "practice"
    ]
  },
  {
    "section": "ela",
    "category": "ela.revising.grammar.clarity_concision",
    "difficulty": 2,
    "type": "multiple_choice",
    "stem": "Practice question 7 for clarity concision",
    "options": [
      {
        "label": "A",
        "text": "Option A"
      },
      {
        "label": "B",
        "text": "Option B"
      },
      {
        "label": "C",
        "text": "Option C"
      },
      {
        "label": "D",
        "text": "Option D"
      }
    ],
    "correctAnswer": "A",
    "explanation": "Detailed explanation for ela.revising.grammar.clarity_concision",
    "commonMistakes": [
      {
        "label": "Common error",
        "explanation": "Students often make this type of mistake."
      },
      {
        "label": "Another mistake",
        "explanation": "This is another frequent error."
      }
    ],
    "skills": [
      "clarity_concision"
    ],
    "tags": [
      "ela",
      "practice"
    ]
  },
  {
    "section": "ela",
    "category": "ela.revising.grammar.clarity_concision",
    "difficulty": 3,
    "type": "multiple_choice",
    "stem": "Practice question 8 for clarity concision",
    "options": [
      {
        "label": "A",
        "text": "Option A"
      },
      {
        "label": "B",
        "text": "Option B"
      },
      {
        "label": "C",
        "text": "Option C"
      },
      {
        "label": "D",
        "text": "Option D"
      }
    ],
    "correctAnswer": "A",
    "explanation": "Detailed explanation for ela.revising.grammar.clarity_concision",
    "commonMistakes": [
      {
        "label": "Common error",
        "explanation": "Students often make this type of mistake."
      },
      {
        "label": "Another mistake",
        "explanation": "This is another frequent error."
      }
    ],
    "skills": [
      "clarity_concision"
    ],
    "tags": [
      "ela",
      "practice"
    ]
  },
  {
    "section": "ela",
    "category": "ela.revising.grammar.clarity_concision",
    "difficulty": 4,
    "type": "multiple_choice",
    "stem": "Practice question 9 for clarity concision",
    "options": [
      {
        "label": "A",
        "text": "Option A"
      },
      {
        "label": "B",
        "text": "Option B"
      },
      {
        "label": "C",
        "text": "Option C"
      },
      {
        "label": "D",
        "text": "Option D"
      }
    ],
    "correctAnswer": "A",
    "explanation": "Detailed explanation for ela.revising.grammar.clarity_concision",
    "commonMistakes": [
      {
        "label": "Common error",
        "explanation": "Students often make this type of mistake."
      },
      {
        "label": "Another mistake",
        "explanation": "This is another frequent error."
      }
    ],
    "skills": [
      "clarity_concision"
    ],
    "tags": [
      "ela",
      "practice"
    ]
  },
  {
    "section": "ela",
    "category": "ela.revising.grammar.clarity_concision",
    "difficulty": 5,
    "type": "multiple_choice",
    "stem": "Practice question 10 for clarity concision",
    "options": [
      {
        "label": "A",
        "text": "Option A"
      },
      {
        "label": "B",
        "text": "Option B"
      },
      {
        "label": "C",
        "text": "Option C"
      },
      {
        "label": "D",
        "text": "Option D"
      }
    ],
    "correctAnswer": "A",
    "explanation": "Detailed explanation for ela.revising.grammar.clarity_concision",
    "commonMistakes": [
      {
        "label": "Common error",
        "explanation": "Students often make this type of mistake."
      },
      {
        "label": "Another mistake",
        "explanation": "This is another frequent error."
      }
    ],
    "skills": [
      "clarity_concision"
    ],
    "tags": [
      "ela",
      "practice"
    ]
  },
  {
    "section": "ela",
    "category": "ela.revising.grammar.wordiness",
    "difficulty": 1,
    "type": "multiple_choice",
    "stem": "Practice question 1 for wordiness",
    "options": [
      {
        "label": "A",
        "text": "Option A"
      },
      {
        "label": "B",
        "text": "Option B"
      },
      {
        "label": "C",
        "text": "Option C"
      },
      {
        "label": "D",
        "text": "Option D"
      }
    ],
    "correctAnswer": "A",
    "explanation": "Detailed explanation for ela.revising.grammar.wordiness",
    "commonMistakes": [
      {
        "label": "Common error",
        "explanation": "Students often make this type of mistake."
      },
      {
        "label": "Another mistake",
        "explanation": "This is another frequent error."
      }
    ],
    "skills": [
      "wordiness"
    ],
    "tags": [
      "ela",
      "practice"
    ]
  },
  {
    "section": "ela",
    "category": "ela.revising.grammar.wordiness",
    "difficulty": 2,
    "type": "multiple_choice",
    "stem": "Practice question 2 for wordiness",
    "options": [
      {
        "label": "A",
        "text": "Option A"
      },
      {
        "label": "B",
        "text": "Option B"
      },
      {
        "label": "C",
        "text": "Option C"
      },
      {
        "label": "D",
        "text": "Option D"
      }
    ],
    "correctAnswer": "A",
    "explanation": "Detailed explanation for ela.revising.grammar.wordiness",
    "commonMistakes": [
      {
        "label": "Common error",
        "explanation": "Students often make this type of mistake."
      },
      {
        "label": "Another mistake",
        "explanation": "This is another frequent error."
      }
    ],
    "skills": [
      "wordiness"
    ],
    "tags": [
      "ela",
      "practice"
    ]
  },
  {
    "section": "ela",
    "category": "ela.revising.grammar.wordiness",
    "difficulty": 3,
    "type": "multiple_choice",
    "stem": "Practice question 3 for wordiness",
    "options": [
      {
        "label": "A",
        "text": "Option A"
      },
      {
        "label": "B",
        "text": "Option B"
      },
      {
        "label": "C",
        "text": "Option C"
      },
      {
        "label": "D",
        "text": "Option D"
      }
    ],
    "correctAnswer": "A",
    "explanation": "Detailed explanation for ela.revising.grammar.wordiness",
    "commonMistakes": [
      {
        "label": "Common error",
        "explanation": "Students often make this type of mistake."
      },
      {
        "label": "Another mistake",
        "explanation": "This is another frequent error."
      }
    ],
    "skills": [
      "wordiness"
    ],
    "tags": [
      "ela",
      "practice"
    ]
  },
  {
    "section": "ela",
    "category": "ela.revising.grammar.wordiness",
    "difficulty": 4,
    "type": "multiple_choice",
    "stem": "Practice question 4 for wordiness",
    "options": [
      {
        "label": "A",
        "text": "Option A"
      },
      {
        "label": "B",
        "text": "Option B"
      },
      {
        "label": "C",
        "text": "Option C"
      },
      {
        "label": "D",
        "text": "Option D"
      }
    ],
    "correctAnswer": "A",
    "explanation": "Detailed explanation for ela.revising.grammar.wordiness",
    "commonMistakes": [
      {
        "label": "Common error",
        "explanation": "Students often make this type of mistake."
      },
      {
        "label": "Another mistake",
        "explanation": "This is another frequent error."
      }
    ],
    "skills": [
      "wordiness"
    ],
    "tags": [
      "ela",
      "practice"
    ]
  },
  {
    "section": "ela",
    "category": "ela.revising.grammar.wordiness",
    "difficulty": 5,
    "type": "multiple_choice",
    "stem": "Practice question 5 for wordiness",
    "options": [
      {
        "label": "A",
        "text": "Option A"
      },
      {
        "label": "B",
        "text": "Option B"
      },
      {
        "label": "C",
        "text": "Option C"
      },
      {
        "label": "D",
        "text": "Option D"
      }
    ],
    "correctAnswer": "A",
    "explanation": "Detailed explanation for ela.revising.grammar.wordiness",
    "commonMistakes": [
      {
        "label": "Common error",
        "explanation": "Students often make this type of mistake."
      },
      {
        "label": "Another mistake",
        "explanation": "This is another frequent error."
      }
    ],
    "skills": [
      "wordiness"
    ],
    "tags": [
      "ela",
      "practice"
    ]
  },
  {
    "section": "ela",
    "category": "ela.revising.grammar.wordiness",
    "difficulty": 1,
    "type": "multiple_choice",
    "stem": "Practice question 6 for wordiness",
    "options": [
      {
        "label": "A",
        "text": "Option A"
      },
      {
        "label": "B",
        "text": "Option B"
      },
      {
        "label": "C",
        "text": "Option C"
      },
      {
        "label": "D",
        "text": "Option D"
      }
    ],
    "correctAnswer": "A",
    "explanation": "Detailed explanation for ela.revising.grammar.wordiness",
    "commonMistakes": [
      {
        "label": "Common error",
        "explanation": "Students often make this type of mistake."
      },
      {
        "label": "Another mistake",
        "explanation": "This is another frequent error."
      }
    ],
    "skills": [
      "wordiness"
    ],
    "tags": [
      "ela",
      "practice"
    ]
  },
  {
    "section": "ela",
    "category": "ela.revising.grammar.wordiness",
    "difficulty": 2,
    "type": "multiple_choice",
    "stem": "Practice question 7 for wordiness",
    "options": [
      {
        "label": "A",
        "text": "Option A"
      },
      {
        "label": "B",
        "text": "Option B"
      },
      {
        "label": "C",
        "text": "Option C"
      },
      {
        "label": "D",
        "text": "Option D"
      }
    ],
    "correctAnswer": "A",
    "explanation": "Detailed explanation for ela.revising.grammar.wordiness",
    "commonMistakes": [
      {
        "label": "Common error",
        "explanation": "Students often make this type of mistake."
      },
      {
        "label": "Another mistake",
        "explanation": "This is another frequent error."
      }
    ],
    "skills": [
      "wordiness"
    ],
    "tags": [
      "ela",
      "practice"
    ]
  },
  {
    "section": "ela",
    "category": "ela.revising.grammar.wordiness",
    "difficulty": 3,
    "type": "multiple_choice",
    "stem": "Practice question 8 for wordiness",
    "options": [
      {
        "label": "A",
        "text": "Option A"
      },
      {
        "label": "B",
        "text": "Option B"
      },
      {
        "label": "C",
        "text": "Option C"
      },
      {
        "label": "D",
        "text": "Option D"
      }
    ],
    "correctAnswer": "A",
    "explanation": "Detailed explanation for ela.revising.grammar.wordiness",
    "commonMistakes": [
      {
        "label": "Common error",
        "explanation": "Students often make this type of mistake."
      },
      {
        "label": "Another mistake",
        "explanation": "This is another frequent error."
      }
    ],
    "skills": [
      "wordiness"
    ],
    "tags": [
      "ela",
      "practice"
    ]
  },
  {
    "section": "ela",
    "category": "ela.revising.grammar.wordiness",
    "difficulty": 4,
    "type": "multiple_choice",
    "stem": "Practice question 9 for wordiness",
    "options": [
      {
        "label": "A",
        "text": "Option A"
      },
      {
        "label": "B",
        "text": "Option B"
      },
      {
        "label": "C",
        "text": "Option C"
      },
      {
        "label": "D",
        "text": "Option D"
      }
    ],
    "correctAnswer": "A",
    "explanation": "Detailed explanation for ela.revising.grammar.wordiness",
    "commonMistakes": [
      {
        "label": "Common error",
        "explanation": "Students often make this type of mistake."
      },
      {
        "label": "Another mistake",
        "explanation": "This is another frequent error."
      }
    ],
    "skills": [
      "wordiness"
    ],
    "tags": [
      "ela",
      "practice"
    ]
  },
  {
    "section": "ela",
    "category": "ela.revising.grammar.wordiness",
    "difficulty": 5,
    "type": "multiple_choice",
    "stem": "Practice question 10 for wordiness",
    "options": [
      {
        "label": "A",
        "text": "Option A"
      },
      {
        "label": "B",
        "text": "Option B"
      },
      {
        "label": "C",
        "text": "Option C"
      },
      {
        "label": "D",
        "text": "Option D"
      }
    ],
    "correctAnswer": "A",
    "explanation": "Detailed explanation for ela.revising.grammar.wordiness",
    "commonMistakes": [
      {
        "label": "Common error",
        "explanation": "Students often make this type of mistake."
      },
      {
        "label": "Another mistake",
        "explanation": "This is another frequent error."
      }
    ],
    "skills": [
      "wordiness"
    ],
    "tags": [
      "ela",
      "practice"
    ]
  },
  {
    "section": "ela",
    "category": "ela.revising.grammar.word_choice",
    "difficulty": 1,
    "type": "multiple_choice",
    "stem": "Practice question 1 for word choice",
    "options": [
      {
        "label": "A",
        "text": "Option A"
      },
      {
        "label": "B",
        "text": "Option B"
      },
      {
        "label": "C",
        "text": "Option C"
      },
      {
        "label": "D",
        "text": "Option D"
      }
    ],
    "correctAnswer": "A",
    "explanation": "Detailed explanation for ela.revising.grammar.word_choice",
    "commonMistakes": [
      {
        "label": "Common error",
        "explanation": "Students often make this type of mistake."
      },
      {
        "label": "Another mistake",
        "explanation": "This is another frequent error."
      }
    ],
    "skills": [
      "word_choice"
    ],
    "tags": [
      "ela",
      "practice"
    ]
  },
  {
    "section": "ela",
    "category": "ela.revising.grammar.word_choice",
    "difficulty": 2,
    "type": "multiple_choice",
    "stem": "Practice question 2 for word choice",
    "options": [
      {
        "label": "A",
        "text": "Option A"
      },
      {
        "label": "B",
        "text": "Option B"
      },
      {
        "label": "C",
        "text": "Option C"
      },
      {
        "label": "D",
        "text": "Option D"
      }
    ],
    "correctAnswer": "A",
    "explanation": "Detailed explanation for ela.revising.grammar.word_choice",
    "commonMistakes": [
      {
        "label": "Common error",
        "explanation": "Students often make this type of mistake."
      },
      {
        "label": "Another mistake",
        "explanation": "This is another frequent error."
      }
    ],
    "skills": [
      "word_choice"
    ],
    "tags": [
      "ela",
      "practice"
    ]
  },
  {
    "section": "ela",
    "category": "ela.revising.grammar.word_choice",
    "difficulty": 3,
    "type": "multiple_choice",
    "stem": "Practice question 3 for word choice",
    "options": [
      {
        "label": "A",
        "text": "Option A"
      },
      {
        "label": "B",
        "text": "Option B"
      },
      {
        "label": "C",
        "text": "Option C"
      },
      {
        "label": "D",
        "text": "Option D"
      }
    ],
    "correctAnswer": "A",
    "explanation": "Detailed explanation for ela.revising.grammar.word_choice",
    "commonMistakes": [
      {
        "label": "Common error",
        "explanation": "Students often make this type of mistake."
      },
      {
        "label": "Another mistake",
        "explanation": "This is another frequent error."
      }
    ],
    "skills": [
      "word_choice"
    ],
    "tags": [
      "ela",
      "practice"
    ]
  },
  {
    "section": "ela",
    "category": "ela.revising.grammar.word_choice",
    "difficulty": 4,
    "type": "multiple_choice",
    "stem": "Practice question 4 for word choice",
    "options": [
      {
        "label": "A",
        "text": "Option A"
      },
      {
        "label": "B",
        "text": "Option B"
      },
      {
        "label": "C",
        "text": "Option C"
      },
      {
        "label": "D",
        "text": "Option D"
      }
    ],
    "correctAnswer": "A",
    "explanation": "Detailed explanation for ela.revising.grammar.word_choice",
    "commonMistakes": [
      {
        "label": "Common error",
        "explanation": "Students often make this type of mistake."
      },
      {
        "label": "Another mistake",
        "explanation": "This is another frequent error."
      }
    ],
    "skills": [
      "word_choice"
    ],
    "tags": [
      "ela",
      "practice"
    ]
  },
  {
    "section": "ela",
    "category": "ela.revising.grammar.word_choice",
    "difficulty": 5,
    "type": "multiple_choice",
    "stem": "Practice question 5 for word choice",
    "options": [
      {
        "label": "A",
        "text": "Option A"
      },
      {
        "label": "B",
        "text": "Option B"
      },
      {
        "label": "C",
        "text": "Option C"
      },
      {
        "label": "D",
        "text": "Option D"
      }
    ],
    "correctAnswer": "A",
    "explanation": "Detailed explanation for ela.revising.grammar.word_choice",
    "commonMistakes": [
      {
        "label": "Common error",
        "explanation": "Students often make this type of mistake."
      },
      {
        "label": "Another mistake",
        "explanation": "This is another frequent error."
      }
    ],
    "skills": [
      "word_choice"
    ],
    "tags": [
      "ela",
      "practice"
    ]
  },
  {
    "section": "ela",
    "category": "ela.revising.grammar.word_choice",
    "difficulty": 1,
    "type": "multiple_choice",
    "stem": "Practice question 6 for word choice",
    "options": [
      {
        "label": "A",
        "text": "Option A"
      },
      {
        "label": "B",
        "text": "Option B"
      },
      {
        "label": "C",
        "text": "Option C"
      },
      {
        "label": "D",
        "text": "Option D"
      }
    ],
    "correctAnswer": "A",
    "explanation": "Detailed explanation for ela.revising.grammar.word_choice",
    "commonMistakes": [
      {
        "label": "Common error",
        "explanation": "Students often make this type of mistake."
      },
      {
        "label": "Another mistake",
        "explanation": "This is another frequent error."
      }
    ],
    "skills": [
      "word_choice"
    ],
    "tags": [
      "ela",
      "practice"
    ]
  },
  {
    "section": "ela",
    "category": "ela.revising.grammar.word_choice",
    "difficulty": 2,
    "type": "multiple_choice",
    "stem": "Practice question 7 for word choice",
    "options": [
      {
        "label": "A",
        "text": "Option A"
      },
      {
        "label": "B",
        "text": "Option B"
      },
      {
        "label": "C",
        "text": "Option C"
      },
      {
        "label": "D",
        "text": "Option D"
      }
    ],
    "correctAnswer": "A",
    "explanation": "Detailed explanation for ela.revising.grammar.word_choice",
    "commonMistakes": [
      {
        "label": "Common error",
        "explanation": "Students often make this type of mistake."
      },
      {
        "label": "Another mistake",
        "explanation": "This is another frequent error."
      }
    ],
    "skills": [
      "word_choice"
    ],
    "tags": [
      "ela",
      "practice"
    ]
  },
  {
    "section": "ela",
    "category": "ela.revising.grammar.word_choice",
    "difficulty": 3,
    "type": "multiple_choice",
    "stem": "Practice question 8 for word choice",
    "options": [
      {
        "label": "A",
        "text": "Option A"
      },
      {
        "label": "B",
        "text": "Option B"
      },
      {
        "label": "C",
        "text": "Option C"
      },
      {
        "label": "D",
        "text": "Option D"
      }
    ],
    "correctAnswer": "A",
    "explanation": "Detailed explanation for ela.revising.grammar.word_choice",
    "commonMistakes": [
      {
        "label": "Common error",
        "explanation": "Students often make this type of mistake."
      },
      {
        "label": "Another mistake",
        "explanation": "This is another frequent error."
      }
    ],
    "skills": [
      "word_choice"
    ],
    "tags": [
      "ela",
      "practice"
    ]
  },
  {
    "section": "ela",
    "category": "ela.revising.grammar.word_choice",
    "difficulty": 4,
    "type": "multiple_choice",
    "stem": "Practice question 9 for word choice",
    "options": [
      {
        "label": "A",
        "text": "Option A"
      },
      {
        "label": "B",
        "text": "Option B"
      },
      {
        "label": "C",
        "text": "Option C"
      },
      {
        "label": "D",
        "text": "Option D"
      }
    ],
    "correctAnswer": "A",
    "explanation": "Detailed explanation for ela.revising.grammar.word_choice",
    "commonMistakes": [
      {
        "label": "Common error",
        "explanation": "Students often make this type of mistake."
      },
      {
        "label": "Another mistake",
        "explanation": "This is another frequent error."
      }
    ],
    "skills": [
      "word_choice"
    ],
    "tags": [
      "ela",
      "practice"
    ]
  },
  {
    "section": "ela",
    "category": "ela.revising.grammar.word_choice",
    "difficulty": 5,
    "type": "multiple_choice",
    "stem": "Practice question 10 for word choice",
    "options": [
      {
        "label": "A",
        "text": "Option A"
      },
      {
        "label": "B",
        "text": "Option B"
      },
      {
        "label": "C",
        "text": "Option C"
      },
      {
        "label": "D",
        "text": "Option D"
      }
    ],
    "correctAnswer": "A",
    "explanation": "Detailed explanation for ela.revising.grammar.word_choice",
    "commonMistakes": [
      {
        "label": "Common error",
        "explanation": "Students often make this type of mistake."
      },
      {
        "label": "Another mistake",
        "explanation": "This is another frequent error."
      }
    ],
    "skills": [
      "word_choice"
    ],
    "tags": [
      "ela",
      "practice"
    ]
  },
  {
    "section": "ela",
    "category": "ela.revising.grammar.transitions",
    "difficulty": 1,
    "type": "multiple_choice",
    "stem": "Practice question 1 for transitions",
    "options": [
      {
        "label": "A",
        "text": "Option A"
      },
      {
        "label": "B",
        "text": "Option B"
      },
      {
        "label": "C",
        "text": "Option C"
      },
      {
        "label": "D",
        "text": "Option D"
      }
    ],
    "correctAnswer": "A",
    "explanation": "Detailed explanation for ela.revising.grammar.transitions",
    "commonMistakes": [
      {
        "label": "Common error",
        "explanation": "Students often make this type of mistake."
      },
      {
        "label": "Another mistake",
        "explanation": "This is another frequent error."
      }
    ],
    "skills": [
      "transitions"
    ],
    "tags": [
      "ela",
      "practice"
    ]
  },
  {
    "section": "ela",
    "category": "ela.revising.grammar.transitions",
    "difficulty": 2,
    "type": "multiple_choice",
    "stem": "Practice question 2 for transitions",
    "options": [
      {
        "label": "A",
        "text": "Option A"
      },
      {
        "label": "B",
        "text": "Option B"
      },
      {
        "label": "C",
        "text": "Option C"
      },
      {
        "label": "D",
        "text": "Option D"
      }
    ],
    "correctAnswer": "A",
    "explanation": "Detailed explanation for ela.revising.grammar.transitions",
    "commonMistakes": [
      {
        "label": "Common error",
        "explanation": "Students often make this type of mistake."
      },
      {
        "label": "Another mistake",
        "explanation": "This is another frequent error."
      }
    ],
    "skills": [
      "transitions"
    ],
    "tags": [
      "ela",
      "practice"
    ]
  },
  {
    "section": "ela",
    "category": "ela.revising.grammar.transitions",
    "difficulty": 3,
    "type": "multiple_choice",
    "stem": "Practice question 3 for transitions",
    "options": [
      {
        "label": "A",
        "text": "Option A"
      },
      {
        "label": "B",
        "text": "Option B"
      },
      {
        "label": "C",
        "text": "Option C"
      },
      {
        "label": "D",
        "text": "Option D"
      }
    ],
    "correctAnswer": "A",
    "explanation": "Detailed explanation for ela.revising.grammar.transitions",
    "commonMistakes": [
      {
        "label": "Common error",
        "explanation": "Students often make this type of mistake."
      },
      {
        "label": "Another mistake",
        "explanation": "This is another frequent error."
      }
    ],
    "skills": [
      "transitions"
    ],
    "tags": [
      "ela",
      "practice"
    ]
  },
  {
    "section": "ela",
    "category": "ela.revising.grammar.transitions",
    "difficulty": 4,
    "type": "multiple_choice",
    "stem": "Practice question 4 for transitions",
    "options": [
      {
        "label": "A",
        "text": "Option A"
      },
      {
        "label": "B",
        "text": "Option B"
      },
      {
        "label": "C",
        "text": "Option C"
      },
      {
        "label": "D",
        "text": "Option D"
      }
    ],
    "correctAnswer": "A",
    "explanation": "Detailed explanation for ela.revising.grammar.transitions",
    "commonMistakes": [
      {
        "label": "Common error",
        "explanation": "Students often make this type of mistake."
      },
      {
        "label": "Another mistake",
        "explanation": "This is another frequent error."
      }
    ],
    "skills": [
      "transitions"
    ],
    "tags": [
      "ela",
      "practice"
    ]
  },
  {
    "section": "ela",
    "category": "ela.revising.grammar.transitions",
    "difficulty": 5,
    "type": "multiple_choice",
    "stem": "Practice question 5 for transitions",
    "options": [
      {
        "label": "A",
        "text": "Option A"
      },
      {
        "label": "B",
        "text": "Option B"
      },
      {
        "label": "C",
        "text": "Option C"
      },
      {
        "label": "D",
        "text": "Option D"
      }
    ],
    "correctAnswer": "A",
    "explanation": "Detailed explanation for ela.revising.grammar.transitions",
    "commonMistakes": [
      {
        "label": "Common error",
        "explanation": "Students often make this type of mistake."
      },
      {
        "label": "Another mistake",
        "explanation": "This is another frequent error."
      }
    ],
    "skills": [
      "transitions"
    ],
    "tags": [
      "ela",
      "practice"
    ]
  },
  {
    "section": "ela",
    "category": "ela.revising.grammar.transitions",
    "difficulty": 1,
    "type": "multiple_choice",
    "stem": "Practice question 6 for transitions",
    "options": [
      {
        "label": "A",
        "text": "Option A"
      },
      {
        "label": "B",
        "text": "Option B"
      },
      {
        "label": "C",
        "text": "Option C"
      },
      {
        "label": "D",
        "text": "Option D"
      }
    ],
    "correctAnswer": "A",
    "explanation": "Detailed explanation for ela.revising.grammar.transitions",
    "commonMistakes": [
      {
        "label": "Common error",
        "explanation": "Students often make this type of mistake."
      },
      {
        "label": "Another mistake",
        "explanation": "This is another frequent error."
      }
    ],
    "skills": [
      "transitions"
    ],
    "tags": [
      "ela",
      "practice"
    ]
  },
  {
    "section": "ela",
    "category": "ela.revising.grammar.transitions",
    "difficulty": 2,
    "type": "multiple_choice",
    "stem": "Practice question 7 for transitions",
    "options": [
      {
        "label": "A",
        "text": "Option A"
      },
      {
        "label": "B",
        "text": "Option B"
      },
      {
        "label": "C",
        "text": "Option C"
      },
      {
        "label": "D",
        "text": "Option D"
      }
    ],
    "correctAnswer": "A",
    "explanation": "Detailed explanation for ela.revising.grammar.transitions",
    "commonMistakes": [
      {
        "label": "Common error",
        "explanation": "Students often make this type of mistake."
      },
      {
        "label": "Another mistake",
        "explanation": "This is another frequent error."
      }
    ],
    "skills": [
      "transitions"
    ],
    "tags": [
      "ela",
      "practice"
    ]
  },
  {
    "section": "ela",
    "category": "ela.revising.grammar.transitions",
    "difficulty": 3,
    "type": "multiple_choice",
    "stem": "Practice question 8 for transitions",
    "options": [
      {
        "label": "A",
        "text": "Option A"
      },
      {
        "label": "B",
        "text": "Option B"
      },
      {
        "label": "C",
        "text": "Option C"
      },
      {
        "label": "D",
        "text": "Option D"
      }
    ],
    "correctAnswer": "A",
    "explanation": "Detailed explanation for ela.revising.grammar.transitions",
    "commonMistakes": [
      {
        "label": "Common error",
        "explanation": "Students often make this type of mistake."
      },
      {
        "label": "Another mistake",
        "explanation": "This is another frequent error."
      }
    ],
    "skills": [
      "transitions"
    ],
    "tags": [
      "ela",
      "practice"
    ]
  },
  {
    "section": "ela",
    "category": "ela.revising.grammar.transitions",
    "difficulty": 4,
    "type": "multiple_choice",
    "stem": "Practice question 9 for transitions",
    "options": [
      {
        "label": "A",
        "text": "Option A"
      },
      {
        "label": "B",
        "text": "Option B"
      },
      {
        "label": "C",
        "text": "Option C"
      },
      {
        "label": "D",
        "text": "Option D"
      }
    ],
    "correctAnswer": "A",
    "explanation": "Detailed explanation for ela.revising.grammar.transitions",
    "commonMistakes": [
      {
        "label": "Common error",
        "explanation": "Students often make this type of mistake."
      },
      {
        "label": "Another mistake",
        "explanation": "This is another frequent error."
      }
    ],
    "skills": [
      "transitions"
    ],
    "tags": [
      "ela",
      "practice"
    ]
  },
  {
    "section": "ela",
    "category": "ela.revising.grammar.transitions",
    "difficulty": 5,
    "type": "multiple_choice",
    "stem": "Practice question 10 for transitions",
    "options": [
      {
        "label": "A",
        "text": "Option A"
      },
      {
        "label": "B",
        "text": "Option B"
      },
      {
        "label": "C",
        "text": "Option C"
      },
      {
        "label": "D",
        "text": "Option D"
      }
    ],
    "correctAnswer": "A",
    "explanation": "Detailed explanation for ela.revising.grammar.transitions",
    "commonMistakes": [
      {
        "label": "Common error",
        "explanation": "Students often make this type of mistake."
      },
      {
        "label": "Another mistake",
        "explanation": "This is another frequent error."
      }
    ],
    "skills": [
      "transitions"
    ],
    "tags": [
      "ela",
      "practice"
    ]
  },
  {
    "section": "ela",
    "category": "ela.revising.style.conciseness",
    "difficulty": 1,
    "type": "multiple_choice",
    "stem": "Practice question 1 for conciseness",
    "options": [
      {
        "label": "A",
        "text": "Option A"
      },
      {
        "label": "B",
        "text": "Option B"
      },
      {
        "label": "C",
        "text": "Option C"
      },
      {
        "label": "D",
        "text": "Option D"
      }
    ],
    "correctAnswer": "A",
    "explanation": "Detailed explanation for ela.revising.style.conciseness",
    "commonMistakes": [
      {
        "label": "Common error",
        "explanation": "Students often make this type of mistake."
      },
      {
        "label": "Another mistake",
        "explanation": "This is another frequent error."
      }
    ],
    "skills": [
      "conciseness"
    ],
    "tags": [
      "ela",
      "practice"
    ]
  },
  {
    "section": "ela",
    "category": "ela.revising.style.conciseness",
    "difficulty": 2,
    "type": "multiple_choice",
    "stem": "Practice question 2 for conciseness",
    "options": [
      {
        "label": "A",
        "text": "Option A"
      },
      {
        "label": "B",
        "text": "Option B"
      },
      {
        "label": "C",
        "text": "Option C"
      },
      {
        "label": "D",
        "text": "Option D"
      }
    ],
    "correctAnswer": "A",
    "explanation": "Detailed explanation for ela.revising.style.conciseness",
    "commonMistakes": [
      {
        "label": "Common error",
        "explanation": "Students often make this type of mistake."
      },
      {
        "label": "Another mistake",
        "explanation": "This is another frequent error."
      }
    ],
    "skills": [
      "conciseness"
    ],
    "tags": [
      "ela",
      "practice"
    ]
  },
  {
    "section": "ela",
    "category": "ela.revising.style.conciseness",
    "difficulty": 3,
    "type": "multiple_choice",
    "stem": "Practice question 3 for conciseness",
    "options": [
      {
        "label": "A",
        "text": "Option A"
      },
      {
        "label": "B",
        "text": "Option B"
      },
      {
        "label": "C",
        "text": "Option C"
      },
      {
        "label": "D",
        "text": "Option D"
      }
    ],
    "correctAnswer": "A",
    "explanation": "Detailed explanation for ela.revising.style.conciseness",
    "commonMistakes": [
      {
        "label": "Common error",
        "explanation": "Students often make this type of mistake."
      },
      {
        "label": "Another mistake",
        "explanation": "This is another frequent error."
      }
    ],
    "skills": [
      "conciseness"
    ],
    "tags": [
      "ela",
      "practice"
    ]
  },
  {
    "section": "ela",
    "category": "ela.revising.style.conciseness",
    "difficulty": 4,
    "type": "multiple_choice",
    "stem": "Practice question 4 for conciseness",
    "options": [
      {
        "label": "A",
        "text": "Option A"
      },
      {
        "label": "B",
        "text": "Option B"
      },
      {
        "label": "C",
        "text": "Option C"
      },
      {
        "label": "D",
        "text": "Option D"
      }
    ],
    "correctAnswer": "A",
    "explanation": "Detailed explanation for ela.revising.style.conciseness",
    "commonMistakes": [
      {
        "label": "Common error",
        "explanation": "Students often make this type of mistake."
      },
      {
        "label": "Another mistake",
        "explanation": "This is another frequent error."
      }
    ],
    "skills": [
      "conciseness"
    ],
    "tags": [
      "ela",
      "practice"
    ]
  },
  {
    "section": "ela",
    "category": "ela.revising.style.conciseness",
    "difficulty": 5,
    "type": "multiple_choice",
    "stem": "Practice question 5 for conciseness",
    "options": [
      {
        "label": "A",
        "text": "Option A"
      },
      {
        "label": "B",
        "text": "Option B"
      },
      {
        "label": "C",
        "text": "Option C"
      },
      {
        "label": "D",
        "text": "Option D"
      }
    ],
    "correctAnswer": "A",
    "explanation": "Detailed explanation for ela.revising.style.conciseness",
    "commonMistakes": [
      {
        "label": "Common error",
        "explanation": "Students often make this type of mistake."
      },
      {
        "label": "Another mistake",
        "explanation": "This is another frequent error."
      }
    ],
    "skills": [
      "conciseness"
    ],
    "tags": [
      "ela",
      "practice"
    ]
  },
  {
    "section": "ela",
    "category": "ela.revising.style.conciseness",
    "difficulty": 1,
    "type": "multiple_choice",
    "stem": "Practice question 6 for conciseness",
    "options": [
      {
        "label": "A",
        "text": "Option A"
      },
      {
        "label": "B",
        "text": "Option B"
      },
      {
        "label": "C",
        "text": "Option C"
      },
      {
        "label": "D",
        "text": "Option D"
      }
    ],
    "correctAnswer": "A",
    "explanation": "Detailed explanation for ela.revising.style.conciseness",
    "commonMistakes": [
      {
        "label": "Common error",
        "explanation": "Students often make this type of mistake."
      },
      {
        "label": "Another mistake",
        "explanation": "This is another frequent error."
      }
    ],
    "skills": [
      "conciseness"
    ],
    "tags": [
      "ela",
      "practice"
    ]
  },
  {
    "section": "ela",
    "category": "ela.revising.style.conciseness",
    "difficulty": 2,
    "type": "multiple_choice",
    "stem": "Practice question 7 for conciseness",
    "options": [
      {
        "label": "A",
        "text": "Option A"
      },
      {
        "label": "B",
        "text": "Option B"
      },
      {
        "label": "C",
        "text": "Option C"
      },
      {
        "label": "D",
        "text": "Option D"
      }
    ],
    "correctAnswer": "A",
    "explanation": "Detailed explanation for ela.revising.style.conciseness",
    "commonMistakes": [
      {
        "label": "Common error",
        "explanation": "Students often make this type of mistake."
      },
      {
        "label": "Another mistake",
        "explanation": "This is another frequent error."
      }
    ],
    "skills": [
      "conciseness"
    ],
    "tags": [
      "ela",
      "practice"
    ]
  },
  {
    "section": "ela",
    "category": "ela.revising.style.conciseness",
    "difficulty": 3,
    "type": "multiple_choice",
    "stem": "Practice question 8 for conciseness",
    "options": [
      {
        "label": "A",
        "text": "Option A"
      },
      {
        "label": "B",
        "text": "Option B"
      },
      {
        "label": "C",
        "text": "Option C"
      },
      {
        "label": "D",
        "text": "Option D"
      }
    ],
    "correctAnswer": "A",
    "explanation": "Detailed explanation for ela.revising.style.conciseness",
    "commonMistakes": [
      {
        "label": "Common error",
        "explanation": "Students often make this type of mistake."
      },
      {
        "label": "Another mistake",
        "explanation": "This is another frequent error."
      }
    ],
    "skills": [
      "conciseness"
    ],
    "tags": [
      "ela",
      "practice"
    ]
  },
  {
    "section": "ela",
    "category": "ela.revising.style.conciseness",
    "difficulty": 4,
    "type": "multiple_choice",
    "stem": "Practice question 9 for conciseness",
    "options": [
      {
        "label": "A",
        "text": "Option A"
      },
      {
        "label": "B",
        "text": "Option B"
      },
      {
        "label": "C",
        "text": "Option C"
      },
      {
        "label": "D",
        "text": "Option D"
      }
    ],
    "correctAnswer": "A",
    "explanation": "Detailed explanation for ela.revising.style.conciseness",
    "commonMistakes": [
      {
        "label": "Common error",
        "explanation": "Students often make this type of mistake."
      },
      {
        "label": "Another mistake",
        "explanation": "This is another frequent error."
      }
    ],
    "skills": [
      "conciseness"
    ],
    "tags": [
      "ela",
      "practice"
    ]
  },
  {
    "section": "ela",
    "category": "ela.revising.style.conciseness",
    "difficulty": 5,
    "type": "multiple_choice",
    "stem": "Practice question 10 for conciseness",
    "options": [
      {
        "label": "A",
        "text": "Option A"
      },
      {
        "label": "B",
        "text": "Option B"
      },
      {
        "label": "C",
        "text": "Option C"
      },
      {
        "label": "D",
        "text": "Option D"
      }
    ],
    "correctAnswer": "A",
    "explanation": "Detailed explanation for ela.revising.style.conciseness",
    "commonMistakes": [
      {
        "label": "Common error",
        "explanation": "Students often make this type of mistake."
      },
      {
        "label": "Another mistake",
        "explanation": "This is another frequent error."
      }
    ],
    "skills": [
      "conciseness"
    ],
    "tags": [
      "ela",
      "practice"
    ]
  },
  {
    "section": "ela",
    "category": "ela.revising.style.precise_language",
    "difficulty": 1,
    "type": "multiple_choice",
    "stem": "Practice question 1 for precise language",
    "options": [
      {
        "label": "A",
        "text": "Option A"
      },
      {
        "label": "B",
        "text": "Option B"
      },
      {
        "label": "C",
        "text": "Option C"
      },
      {
        "label": "D",
        "text": "Option D"
      }
    ],
    "correctAnswer": "A",
    "explanation": "Detailed explanation for ela.revising.style.precise_language",
    "commonMistakes": [
      {
        "label": "Common error",
        "explanation": "Students often make this type of mistake."
      },
      {
        "label": "Another mistake",
        "explanation": "This is another frequent error."
      }
    ],
    "skills": [
      "precise_language"
    ],
    "tags": [
      "ela",
      "practice"
    ]
  },
  {
    "section": "ela",
    "category": "ela.revising.style.precise_language",
    "difficulty": 2,
    "type": "multiple_choice",
    "stem": "Practice question 2 for precise language",
    "options": [
      {
        "label": "A",
        "text": "Option A"
      },
      {
        "label": "B",
        "text": "Option B"
      },
      {
        "label": "C",
        "text": "Option C"
      },
      {
        "label": "D",
        "text": "Option D"
      }
    ],
    "correctAnswer": "A",
    "explanation": "Detailed explanation for ela.revising.style.precise_language",
    "commonMistakes": [
      {
        "label": "Common error",
        "explanation": "Students often make this type of mistake."
      },
      {
        "label": "Another mistake",
        "explanation": "This is another frequent error."
      }
    ],
    "skills": [
      "precise_language"
    ],
    "tags": [
      "ela",
      "practice"
    ]
  },
  {
    "section": "ela",
    "category": "ela.revising.style.precise_language",
    "difficulty": 3,
    "type": "multiple_choice",
    "stem": "Practice question 3 for precise language",
    "options": [
      {
        "label": "A",
        "text": "Option A"
      },
      {
        "label": "B",
        "text": "Option B"
      },
      {
        "label": "C",
        "text": "Option C"
      },
      {
        "label": "D",
        "text": "Option D"
      }
    ],
    "correctAnswer": "A",
    "explanation": "Detailed explanation for ela.revising.style.precise_language",
    "commonMistakes": [
      {
        "label": "Common error",
        "explanation": "Students often make this type of mistake."
      },
      {
        "label": "Another mistake",
        "explanation": "This is another frequent error."
      }
    ],
    "skills": [
      "precise_language"
    ],
    "tags": [
      "ela",
      "practice"
    ]
  },
  {
    "section": "ela",
    "category": "ela.revising.style.precise_language",
    "difficulty": 4,
    "type": "multiple_choice",
    "stem": "Practice question 4 for precise language",
    "options": [
      {
        "label": "A",
        "text": "Option A"
      },
      {
        "label": "B",
        "text": "Option B"
      },
      {
        "label": "C",
        "text": "Option C"
      },
      {
        "label": "D",
        "text": "Option D"
      }
    ],
    "correctAnswer": "A",
    "explanation": "Detailed explanation for ela.revising.style.precise_language",
    "commonMistakes": [
      {
        "label": "Common error",
        "explanation": "Students often make this type of mistake."
      },
      {
        "label": "Another mistake",
        "explanation": "This is another frequent error."
      }
    ],
    "skills": [
      "precise_language"
    ],
    "tags": [
      "ela",
      "practice"
    ]
  },
  {
    "section": "ela",
    "category": "ela.revising.style.precise_language",
    "difficulty": 5,
    "type": "multiple_choice",
    "stem": "Practice question 5 for precise language",
    "options": [
      {
        "label": "A",
        "text": "Option A"
      },
      {
        "label": "B",
        "text": "Option B"
      },
      {
        "label": "C",
        "text": "Option C"
      },
      {
        "label": "D",
        "text": "Option D"
      }
    ],
    "correctAnswer": "A",
    "explanation": "Detailed explanation for ela.revising.style.precise_language",
    "commonMistakes": [
      {
        "label": "Common error",
        "explanation": "Students often make this type of mistake."
      },
      {
        "label": "Another mistake",
        "explanation": "This is another frequent error."
      }
    ],
    "skills": [
      "precise_language"
    ],
    "tags": [
      "ela",
      "practice"
    ]
  },
  {
    "section": "ela",
    "category": "ela.revising.style.precise_language",
    "difficulty": 1,
    "type": "multiple_choice",
    "stem": "Practice question 6 for precise language",
    "options": [
      {
        "label": "A",
        "text": "Option A"
      },
      {
        "label": "B",
        "text": "Option B"
      },
      {
        "label": "C",
        "text": "Option C"
      },
      {
        "label": "D",
        "text": "Option D"
      }
    ],
    "correctAnswer": "A",
    "explanation": "Detailed explanation for ela.revising.style.precise_language",
    "commonMistakes": [
      {
        "label": "Common error",
        "explanation": "Students often make this type of mistake."
      },
      {
        "label": "Another mistake",
        "explanation": "This is another frequent error."
      }
    ],
    "skills": [
      "precise_language"
    ],
    "tags": [
      "ela",
      "practice"
    ]
  },
  {
    "section": "ela",
    "category": "ela.revising.style.precise_language",
    "difficulty": 2,
    "type": "multiple_choice",
    "stem": "Practice question 7 for precise language",
    "options": [
      {
        "label": "A",
        "text": "Option A"
      },
      {
        "label": "B",
        "text": "Option B"
      },
      {
        "label": "C",
        "text": "Option C"
      },
      {
        "label": "D",
        "text": "Option D"
      }
    ],
    "correctAnswer": "A",
    "explanation": "Detailed explanation for ela.revising.style.precise_language",
    "commonMistakes": [
      {
        "label": "Common error",
        "explanation": "Students often make this type of mistake."
      },
      {
        "label": "Another mistake",
        "explanation": "This is another frequent error."
      }
    ],
    "skills": [
      "precise_language"
    ],
    "tags": [
      "ela",
      "practice"
    ]
  },
  {
    "section": "ela",
    "category": "ela.revising.style.precise_language",
    "difficulty": 3,
    "type": "multiple_choice",
    "stem": "Practice question 8 for precise language",
    "options": [
      {
        "label": "A",
        "text": "Option A"
      },
      {
        "label": "B",
        "text": "Option B"
      },
      {
        "label": "C",
        "text": "Option C"
      },
      {
        "label": "D",
        "text": "Option D"
      }
    ],
    "correctAnswer": "A",
    "explanation": "Detailed explanation for ela.revising.style.precise_language",
    "commonMistakes": [
      {
        "label": "Common error",
        "explanation": "Students often make this type of mistake."
      },
      {
        "label": "Another mistake",
        "explanation": "This is another frequent error."
      }
    ],
    "skills": [
      "precise_language"
    ],
    "tags": [
      "ela",
      "practice"
    ]
  },
  {
    "section": "ela",
    "category": "ela.revising.style.precise_language",
    "difficulty": 4,
    "type": "multiple_choice",
    "stem": "Practice question 9 for precise language",
    "options": [
      {
        "label": "A",
        "text": "Option A"
      },
      {
        "label": "B",
        "text": "Option B"
      },
      {
        "label": "C",
        "text": "Option C"
      },
      {
        "label": "D",
        "text": "Option D"
      }
    ],
    "correctAnswer": "A",
    "explanation": "Detailed explanation for ela.revising.style.precise_language",
    "commonMistakes": [
      {
        "label": "Common error",
        "explanation": "Students often make this type of mistake."
      },
      {
        "label": "Another mistake",
        "explanation": "This is another frequent error."
      }
    ],
    "skills": [
      "precise_language"
    ],
    "tags": [
      "ela",
      "practice"
    ]
  },
  {
    "section": "ela",
    "category": "ela.revising.style.precise_language",
    "difficulty": 5,
    "type": "multiple_choice",
    "stem": "Practice question 10 for precise language",
    "options": [
      {
        "label": "A",
        "text": "Option A"
      },
      {
        "label": "B",
        "text": "Option B"
      },
      {
        "label": "C",
        "text": "Option C"
      },
      {
        "label": "D",
        "text": "Option D"
      }
    ],
    "correctAnswer": "A",
    "explanation": "Detailed explanation for ela.revising.style.precise_language",
    "commonMistakes": [
      {
        "label": "Common error",
        "explanation": "Students often make this type of mistake."
      },
      {
        "label": "Another mistake",
        "explanation": "This is another frequent error."
      }
    ],
    "skills": [
      "precise_language"
    ],
    "tags": [
      "ela",
      "practice"
    ]
  },
  {
    "section": "ela",
    "category": "ela.revising.style.active_passive",
    "difficulty": 1,
    "type": "multiple_choice",
    "stem": "Practice question 1 for active passive",
    "options": [
      {
        "label": "A",
        "text": "Option A"
      },
      {
        "label": "B",
        "text": "Option B"
      },
      {
        "label": "C",
        "text": "Option C"
      },
      {
        "label": "D",
        "text": "Option D"
      }
    ],
    "correctAnswer": "A",
    "explanation": "Detailed explanation for ela.revising.style.active_passive",
    "commonMistakes": [
      {
        "label": "Common error",
        "explanation": "Students often make this type of mistake."
      },
      {
        "label": "Another mistake",
        "explanation": "This is another frequent error."
      }
    ],
    "skills": [
      "active_passive"
    ],
    "tags": [
      "ela",
      "practice"
    ]
  },
  {
    "section": "ela",
    "category": "ela.revising.style.active_passive",
    "difficulty": 2,
    "type": "multiple_choice",
    "stem": "Practice question 2 for active passive",
    "options": [
      {
        "label": "A",
        "text": "Option A"
      },
      {
        "label": "B",
        "text": "Option B"
      },
      {
        "label": "C",
        "text": "Option C"
      },
      {
        "label": "D",
        "text": "Option D"
      }
    ],
    "correctAnswer": "A",
    "explanation": "Detailed explanation for ela.revising.style.active_passive",
    "commonMistakes": [
      {
        "label": "Common error",
        "explanation": "Students often make this type of mistake."
      },
      {
        "label": "Another mistake",
        "explanation": "This is another frequent error."
      }
    ],
    "skills": [
      "active_passive"
    ],
    "tags": [
      "ela",
      "practice"
    ]
  },
  {
    "section": "ela",
    "category": "ela.revising.style.active_passive",
    "difficulty": 3,
    "type": "multiple_choice",
    "stem": "Practice question 3 for active passive",
    "options": [
      {
        "label": "A",
        "text": "Option A"
      },
      {
        "label": "B",
        "text": "Option B"
      },
      {
        "label": "C",
        "text": "Option C"
      },
      {
        "label": "D",
        "text": "Option D"
      }
    ],
    "correctAnswer": "A",
    "explanation": "Detailed explanation for ela.revising.style.active_passive",
    "commonMistakes": [
      {
        "label": "Common error",
        "explanation": "Students often make this type of mistake."
      },
      {
        "label": "Another mistake",
        "explanation": "This is another frequent error."
      }
    ],
    "skills": [
      "active_passive"
    ],
    "tags": [
      "ela",
      "practice"
    ]
  },
  {
    "section": "ela",
    "category": "ela.revising.style.active_passive",
    "difficulty": 4,
    "type": "multiple_choice",
    "stem": "Practice question 4 for active passive",
    "options": [
      {
        "label": "A",
        "text": "Option A"
      },
      {
        "label": "B",
        "text": "Option B"
      },
      {
        "label": "C",
        "text": "Option C"
      },
      {
        "label": "D",
        "text": "Option D"
      }
    ],
    "correctAnswer": "A",
    "explanation": "Detailed explanation for ela.revising.style.active_passive",
    "commonMistakes": [
      {
        "label": "Common error",
        "explanation": "Students often make this type of mistake."
      },
      {
        "label": "Another mistake",
        "explanation": "This is another frequent error."
      }
    ],
    "skills": [
      "active_passive"
    ],
    "tags": [
      "ela",
      "practice"
    ]
  },
  {
    "section": "ela",
    "category": "ela.revising.style.active_passive",
    "difficulty": 5,
    "type": "multiple_choice",
    "stem": "Practice question 5 for active passive",
    "options": [
      {
        "label": "A",
        "text": "Option A"
      },
      {
        "label": "B",
        "text": "Option B"
      },
      {
        "label": "C",
        "text": "Option C"
      },
      {
        "label": "D",
        "text": "Option D"
      }
    ],
    "correctAnswer": "A",
    "explanation": "Detailed explanation for ela.revising.style.active_passive",
    "commonMistakes": [
      {
        "label": "Common error",
        "explanation": "Students often make this type of mistake."
      },
      {
        "label": "Another mistake",
        "explanation": "This is another frequent error."
      }
    ],
    "skills": [
      "active_passive"
    ],
    "tags": [
      "ela",
      "practice"
    ]
  },
  {
    "section": "ela",
    "category": "ela.revising.style.active_passive",
    "difficulty": 1,
    "type": "multiple_choice",
    "stem": "Practice question 6 for active passive",
    "options": [
      {
        "label": "A",
        "text": "Option A"
      },
      {
        "label": "B",
        "text": "Option B"
      },
      {
        "label": "C",
        "text": "Option C"
      },
      {
        "label": "D",
        "text": "Option D"
      }
    ],
    "correctAnswer": "A",
    "explanation": "Detailed explanation for ela.revising.style.active_passive",
    "commonMistakes": [
      {
        "label": "Common error",
        "explanation": "Students often make this type of mistake."
      },
      {
        "label": "Another mistake",
        "explanation": "This is another frequent error."
      }
    ],
    "skills": [
      "active_passive"
    ],
    "tags": [
      "ela",
      "practice"
    ]
  },
  {
    "section": "ela",
    "category": "ela.revising.style.active_passive",
    "difficulty": 2,
    "type": "multiple_choice",
    "stem": "Practice question 7 for active passive",
    "options": [
      {
        "label": "A",
        "text": "Option A"
      },
      {
        "label": "B",
        "text": "Option B"
      },
      {
        "label": "C",
        "text": "Option C"
      },
      {
        "label": "D",
        "text": "Option D"
      }
    ],
    "correctAnswer": "A",
    "explanation": "Detailed explanation for ela.revising.style.active_passive",
    "commonMistakes": [
      {
        "label": "Common error",
        "explanation": "Students often make this type of mistake."
      },
      {
        "label": "Another mistake",
        "explanation": "This is another frequent error."
      }
    ],
    "skills": [
      "active_passive"
    ],
    "tags": [
      "ela",
      "practice"
    ]
  },
  {
    "section": "ela",
    "category": "ela.revising.style.active_passive",
    "difficulty": 3,
    "type": "multiple_choice",
    "stem": "Practice question 8 for active passive",
    "options": [
      {
        "label": "A",
        "text": "Option A"
      },
      {
        "label": "B",
        "text": "Option B"
      },
      {
        "label": "C",
        "text": "Option C"
      },
      {
        "label": "D",
        "text": "Option D"
      }
    ],
    "correctAnswer": "A",
    "explanation": "Detailed explanation for ela.revising.style.active_passive",
    "commonMistakes": [
      {
        "label": "Common error",
        "explanation": "Students often make this type of mistake."
      },
      {
        "label": "Another mistake",
        "explanation": "This is another frequent error."
      }
    ],
    "skills": [
      "active_passive"
    ],
    "tags": [
      "ela",
      "practice"
    ]
  },
  {
    "section": "ela",
    "category": "ela.revising.style.active_passive",
    "difficulty": 4,
    "type": "multiple_choice",
    "stem": "Practice question 9 for active passive",
    "options": [
      {
        "label": "A",
        "text": "Option A"
      },
      {
        "label": "B",
        "text": "Option B"
      },
      {
        "label": "C",
        "text": "Option C"
      },
      {
        "label": "D",
        "text": "Option D"
      }
    ],
    "correctAnswer": "A",
    "explanation": "Detailed explanation for ela.revising.style.active_passive",
    "commonMistakes": [
      {
        "label": "Common error",
        "explanation": "Students often make this type of mistake."
      },
      {
        "label": "Another mistake",
        "explanation": "This is another frequent error."
      }
    ],
    "skills": [
      "active_passive"
    ],
    "tags": [
      "ela",
      "practice"
    ]
  },
  {
    "section": "ela",
    "category": "ela.revising.style.active_passive",
    "difficulty": 5,
    "type": "multiple_choice",
    "stem": "Practice question 10 for active passive",
    "options": [
      {
        "label": "A",
        "text": "Option A"
      },
      {
        "label": "B",
        "text": "Option B"
      },
      {
        "label": "C",
        "text": "Option C"
      },
      {
        "label": "D",
        "text": "Option D"
      }
    ],
    "correctAnswer": "A",
    "explanation": "Detailed explanation for ela.revising.style.active_passive",
    "commonMistakes": [
      {
        "label": "Common error",
        "explanation": "Students often make this type of mistake."
      },
      {
        "label": "Another mistake",
        "explanation": "This is another frequent error."
      }
    ],
    "skills": [
      "active_passive"
    ],
    "tags": [
      "ela",
      "practice"
    ]
  },
  {
    "section": "ela",
    "category": "ela.revising.style.audience_register",
    "difficulty": 1,
    "type": "multiple_choice",
    "stem": "Practice question 1 for audience register",
    "options": [
      {
        "label": "A",
        "text": "Option A"
      },
      {
        "label": "B",
        "text": "Option B"
      },
      {
        "label": "C",
        "text": "Option C"
      },
      {
        "label": "D",
        "text": "Option D"
      }
    ],
    "correctAnswer": "A",
    "explanation": "Detailed explanation for ela.revising.style.audience_register",
    "commonMistakes": [
      {
        "label": "Common error",
        "explanation": "Students often make this type of mistake."
      },
      {
        "label": "Another mistake",
        "explanation": "This is another frequent error."
      }
    ],
    "skills": [
      "audience_register"
    ],
    "tags": [
      "ela",
      "practice"
    ]
  },
  {
    "section": "ela",
    "category": "ela.revising.style.audience_register",
    "difficulty": 2,
    "type": "multiple_choice",
    "stem": "Practice question 2 for audience register",
    "options": [
      {
        "label": "A",
        "text": "Option A"
      },
      {
        "label": "B",
        "text": "Option B"
      },
      {
        "label": "C",
        "text": "Option C"
      },
      {
        "label": "D",
        "text": "Option D"
      }
    ],
    "correctAnswer": "A",
    "explanation": "Detailed explanation for ela.revising.style.audience_register",
    "commonMistakes": [
      {
        "label": "Common error",
        "explanation": "Students often make this type of mistake."
      },
      {
        "label": "Another mistake",
        "explanation": "This is another frequent error."
      }
    ],
    "skills": [
      "audience_register"
    ],
    "tags": [
      "ela",
      "practice"
    ]
  },
  {
    "section": "ela",
    "category": "ela.revising.style.audience_register",
    "difficulty": 3,
    "type": "multiple_choice",
    "stem": "Practice question 3 for audience register",
    "options": [
      {
        "label": "A",
        "text": "Option A"
      },
      {
        "label": "B",
        "text": "Option B"
      },
      {
        "label": "C",
        "text": "Option C"
      },
      {
        "label": "D",
        "text": "Option D"
      }
    ],
    "correctAnswer": "A",
    "explanation": "Detailed explanation for ela.revising.style.audience_register",
    "commonMistakes": [
      {
        "label": "Common error",
        "explanation": "Students often make this type of mistake."
      },
      {
        "label": "Another mistake",
        "explanation": "This is another frequent error."
      }
    ],
    "skills": [
      "audience_register"
    ],
    "tags": [
      "ela",
      "practice"
    ]
  },
  {
    "section": "ela",
    "category": "ela.revising.style.audience_register",
    "difficulty": 4,
    "type": "multiple_choice",
    "stem": "Practice question 4 for audience register",
    "options": [
      {
        "label": "A",
        "text": "Option A"
      },
      {
        "label": "B",
        "text": "Option B"
      },
      {
        "label": "C",
        "text": "Option C"
      },
      {
        "label": "D",
        "text": "Option D"
      }
    ],
    "correctAnswer": "A",
    "explanation": "Detailed explanation for ela.revising.style.audience_register",
    "commonMistakes": [
      {
        "label": "Common error",
        "explanation": "Students often make this type of mistake."
      },
      {
        "label": "Another mistake",
        "explanation": "This is another frequent error."
      }
    ],
    "skills": [
      "audience_register"
    ],
    "tags": [
      "ela",
      "practice"
    ]
  },
  {
    "section": "ela",
    "category": "ela.revising.style.audience_register",
    "difficulty": 5,
    "type": "multiple_choice",
    "stem": "Practice question 5 for audience register",
    "options": [
      {
        "label": "A",
        "text": "Option A"
      },
      {
        "label": "B",
        "text": "Option B"
      },
      {
        "label": "C",
        "text": "Option C"
      },
      {
        "label": "D",
        "text": "Option D"
      }
    ],
    "correctAnswer": "A",
    "explanation": "Detailed explanation for ela.revising.style.audience_register",
    "commonMistakes": [
      {
        "label": "Common error",
        "explanation": "Students often make this type of mistake."
      },
      {
        "label": "Another mistake",
        "explanation": "This is another frequent error."
      }
    ],
    "skills": [
      "audience_register"
    ],
    "tags": [
      "ela",
      "practice"
    ]
  },
  {
    "section": "ela",
    "category": "ela.revising.style.audience_register",
    "difficulty": 1,
    "type": "multiple_choice",
    "stem": "Practice question 6 for audience register",
    "options": [
      {
        "label": "A",
        "text": "Option A"
      },
      {
        "label": "B",
        "text": "Option B"
      },
      {
        "label": "C",
        "text": "Option C"
      },
      {
        "label": "D",
        "text": "Option D"
      }
    ],
    "correctAnswer": "A",
    "explanation": "Detailed explanation for ela.revising.style.audience_register",
    "commonMistakes": [
      {
        "label": "Common error",
        "explanation": "Students often make this type of mistake."
      },
      {
        "label": "Another mistake",
        "explanation": "This is another frequent error."
      }
    ],
    "skills": [
      "audience_register"
    ],
    "tags": [
      "ela",
      "practice"
    ]
  },
  {
    "section": "ela",
    "category": "ela.revising.style.audience_register",
    "difficulty": 2,
    "type": "multiple_choice",
    "stem": "Practice question 7 for audience register",
    "options": [
      {
        "label": "A",
        "text": "Option A"
      },
      {
        "label": "B",
        "text": "Option B"
      },
      {
        "label": "C",
        "text": "Option C"
      },
      {
        "label": "D",
        "text": "Option D"
      }
    ],
    "correctAnswer": "A",
    "explanation": "Detailed explanation for ela.revising.style.audience_register",
    "commonMistakes": [
      {
        "label": "Common error",
        "explanation": "Students often make this type of mistake."
      },
      {
        "label": "Another mistake",
        "explanation": "This is another frequent error."
      }
    ],
    "skills": [
      "audience_register"
    ],
    "tags": [
      "ela",
      "practice"
    ]
  },
  {
    "section": "ela",
    "category": "ela.revising.style.audience_register",
    "difficulty": 3,
    "type": "multiple_choice",
    "stem": "Practice question 8 for audience register",
    "options": [
      {
        "label": "A",
        "text": "Option A"
      },
      {
        "label": "B",
        "text": "Option B"
      },
      {
        "label": "C",
        "text": "Option C"
      },
      {
        "label": "D",
        "text": "Option D"
      }
    ],
    "correctAnswer": "A",
    "explanation": "Detailed explanation for ela.revising.style.audience_register",
    "commonMistakes": [
      {
        "label": "Common error",
        "explanation": "Students often make this type of mistake."
      },
      {
        "label": "Another mistake",
        "explanation": "This is another frequent error."
      }
    ],
    "skills": [
      "audience_register"
    ],
    "tags": [
      "ela",
      "practice"
    ]
  },
  {
    "section": "ela",
    "category": "ela.revising.style.audience_register",
    "difficulty": 4,
    "type": "multiple_choice",
    "stem": "Practice question 9 for audience register",
    "options": [
      {
        "label": "A",
        "text": "Option A"
      },
      {
        "label": "B",
        "text": "Option B"
      },
      {
        "label": "C",
        "text": "Option C"
      },
      {
        "label": "D",
        "text": "Option D"
      }
    ],
    "correctAnswer": "A",
    "explanation": "Detailed explanation for ela.revising.style.audience_register",
    "commonMistakes": [
      {
        "label": "Common error",
        "explanation": "Students often make this type of mistake."
      },
      {
        "label": "Another mistake",
        "explanation": "This is another frequent error."
      }
    ],
    "skills": [
      "audience_register"
    ],
    "tags": [
      "ela",
      "practice"
    ]
  },
  {
    "section": "ela",
    "category": "ela.revising.style.audience_register",
    "difficulty": 5,
    "type": "multiple_choice",
    "stem": "Practice question 10 for audience register",
    "options": [
      {
        "label": "A",
        "text": "Option A"
      },
      {
        "label": "B",
        "text": "Option B"
      },
      {
        "label": "C",
        "text": "Option C"
      },
      {
        "label": "D",
        "text": "Option D"
      }
    ],
    "correctAnswer": "A",
    "explanation": "Detailed explanation for ela.revising.style.audience_register",
    "commonMistakes": [
      {
        "label": "Common error",
        "explanation": "Students often make this type of mistake."
      },
      {
        "label": "Another mistake",
        "explanation": "This is another frequent error."
      }
    ],
    "skills": [
      "audience_register"
    ],
    "tags": [
      "ela",
      "practice"
    ]
  },
  {
    "section": "ela",
    "category": "ela.revising.style.sentence_combining",
    "difficulty": 1,
    "type": "multiple_choice",
    "stem": "Practice question 1 for sentence combining",
    "options": [
      {
        "label": "A",
        "text": "Option A"
      },
      {
        "label": "B",
        "text": "Option B"
      },
      {
        "label": "C",
        "text": "Option C"
      },
      {
        "label": "D",
        "text": "Option D"
      }
    ],
    "correctAnswer": "A",
    "explanation": "Detailed explanation for ela.revising.style.sentence_combining",
    "commonMistakes": [
      {
        "label": "Common error",
        "explanation": "Students often make this type of mistake."
      },
      {
        "label": "Another mistake",
        "explanation": "This is another frequent error."
      }
    ],
    "skills": [
      "sentence_combining"
    ],
    "tags": [
      "ela",
      "practice"
    ]
  },
  {
    "section": "ela",
    "category": "ela.revising.style.sentence_combining",
    "difficulty": 2,
    "type": "multiple_choice",
    "stem": "Practice question 2 for sentence combining",
    "options": [
      {
        "label": "A",
        "text": "Option A"
      },
      {
        "label": "B",
        "text": "Option B"
      },
      {
        "label": "C",
        "text": "Option C"
      },
      {
        "label": "D",
        "text": "Option D"
      }
    ],
    "correctAnswer": "A",
    "explanation": "Detailed explanation for ela.revising.style.sentence_combining",
    "commonMistakes": [
      {
        "label": "Common error",
        "explanation": "Students often make this type of mistake."
      },
      {
        "label": "Another mistake",
        "explanation": "This is another frequent error."
      }
    ],
    "skills": [
      "sentence_combining"
    ],
    "tags": [
      "ela",
      "practice"
    ]
  },
  {
    "section": "ela",
    "category": "ela.revising.style.sentence_combining",
    "difficulty": 3,
    "type": "multiple_choice",
    "stem": "Practice question 3 for sentence combining",
    "options": [
      {
        "label": "A",
        "text": "Option A"
      },
      {
        "label": "B",
        "text": "Option B"
      },
      {
        "label": "C",
        "text": "Option C"
      },
      {
        "label": "D",
        "text": "Option D"
      }
    ],
    "correctAnswer": "A",
    "explanation": "Detailed explanation for ela.revising.style.sentence_combining",
    "commonMistakes": [
      {
        "label": "Common error",
        "explanation": "Students often make this type of mistake."
      },
      {
        "label": "Another mistake",
        "explanation": "This is another frequent error."
      }
    ],
    "skills": [
      "sentence_combining"
    ],
    "tags": [
      "ela",
      "practice"
    ]
  },
  {
    "section": "ela",
    "category": "ela.revising.style.sentence_combining",
    "difficulty": 4,
    "type": "multiple_choice",
    "stem": "Practice question 4 for sentence combining",
    "options": [
      {
        "label": "A",
        "text": "Option A"
      },
      {
        "label": "B",
        "text": "Option B"
      },
      {
        "label": "C",
        "text": "Option C"
      },
      {
        "label": "D",
        "text": "Option D"
      }
    ],
    "correctAnswer": "A",
    "explanation": "Detailed explanation for ela.revising.style.sentence_combining",
    "commonMistakes": [
      {
        "label": "Common error",
        "explanation": "Students often make this type of mistake."
      },
      {
        "label": "Another mistake",
        "explanation": "This is another frequent error."
      }
    ],
    "skills": [
      "sentence_combining"
    ],
    "tags": [
      "ela",
      "practice"
    ]
  },
  {
    "section": "ela",
    "category": "ela.revising.style.sentence_combining",
    "difficulty": 5,
    "type": "multiple_choice",
    "stem": "Practice question 5 for sentence combining",
    "options": [
      {
        "label": "A",
        "text": "Option A"
      },
      {
        "label": "B",
        "text": "Option B"
      },
      {
        "label": "C",
        "text": "Option C"
      },
      {
        "label": "D",
        "text": "Option D"
      }
    ],
    "correctAnswer": "A",
    "explanation": "Detailed explanation for ela.revising.style.sentence_combining",
    "commonMistakes": [
      {
        "label": "Common error",
        "explanation": "Students often make this type of mistake."
      },
      {
        "label": "Another mistake",
        "explanation": "This is another frequent error."
      }
    ],
    "skills": [
      "sentence_combining"
    ],
    "tags": [
      "ela",
      "practice"
    ]
  },
  {
    "section": "ela",
    "category": "ela.revising.style.sentence_combining",
    "difficulty": 1,
    "type": "multiple_choice",
    "stem": "Practice question 6 for sentence combining",
    "options": [
      {
        "label": "A",
        "text": "Option A"
      },
      {
        "label": "B",
        "text": "Option B"
      },
      {
        "label": "C",
        "text": "Option C"
      },
      {
        "label": "D",
        "text": "Option D"
      }
    ],
    "correctAnswer": "A",
    "explanation": "Detailed explanation for ela.revising.style.sentence_combining",
    "commonMistakes": [
      {
        "label": "Common error",
        "explanation": "Students often make this type of mistake."
      },
      {
        "label": "Another mistake",
        "explanation": "This is another frequent error."
      }
    ],
    "skills": [
      "sentence_combining"
    ],
    "tags": [
      "ela",
      "practice"
    ]
  },
  {
    "section": "ela",
    "category": "ela.revising.style.sentence_combining",
    "difficulty": 2,
    "type": "multiple_choice",
    "stem": "Practice question 7 for sentence combining",
    "options": [
      {
        "label": "A",
        "text": "Option A"
      },
      {
        "label": "B",
        "text": "Option B"
      },
      {
        "label": "C",
        "text": "Option C"
      },
      {
        "label": "D",
        "text": "Option D"
      }
    ],
    "correctAnswer": "A",
    "explanation": "Detailed explanation for ela.revising.style.sentence_combining",
    "commonMistakes": [
      {
        "label": "Common error",
        "explanation": "Students often make this type of mistake."
      },
      {
        "label": "Another mistake",
        "explanation": "This is another frequent error."
      }
    ],
    "skills": [
      "sentence_combining"
    ],
    "tags": [
      "ela",
      "practice"
    ]
  },
  {
    "section": "ela",
    "category": "ela.revising.style.sentence_combining",
    "difficulty": 3,
    "type": "multiple_choice",
    "stem": "Practice question 8 for sentence combining",
    "options": [
      {
        "label": "A",
        "text": "Option A"
      },
      {
        "label": "B",
        "text": "Option B"
      },
      {
        "label": "C",
        "text": "Option C"
      },
      {
        "label": "D",
        "text": "Option D"
      }
    ],
    "correctAnswer": "A",
    "explanation": "Detailed explanation for ela.revising.style.sentence_combining",
    "commonMistakes": [
      {
        "label": "Common error",
        "explanation": "Students often make this type of mistake."
      },
      {
        "label": "Another mistake",
        "explanation": "This is another frequent error."
      }
    ],
    "skills": [
      "sentence_combining"
    ],
    "tags": [
      "ela",
      "practice"
    ]
  },
  {
    "section": "ela",
    "category": "ela.revising.style.sentence_combining",
    "difficulty": 4,
    "type": "multiple_choice",
    "stem": "Practice question 9 for sentence combining",
    "options": [
      {
        "label": "A",
        "text": "Option A"
      },
      {
        "label": "B",
        "text": "Option B"
      },
      {
        "label": "C",
        "text": "Option C"
      },
      {
        "label": "D",
        "text": "Option D"
      }
    ],
    "correctAnswer": "A",
    "explanation": "Detailed explanation for ela.revising.style.sentence_combining",
    "commonMistakes": [
      {
        "label": "Common error",
        "explanation": "Students often make this type of mistake."
      },
      {
        "label": "Another mistake",
        "explanation": "This is another frequent error."
      }
    ],
    "skills": [
      "sentence_combining"
    ],
    "tags": [
      "ela",
      "practice"
    ]
  },
  {
    "section": "ela",
    "category": "ela.revising.style.sentence_combining",
    "difficulty": 5,
    "type": "multiple_choice",
    "stem": "Practice question 10 for sentence combining",
    "options": [
      {
        "label": "A",
        "text": "Option A"
      },
      {
        "label": "B",
        "text": "Option B"
      },
      {
        "label": "C",
        "text": "Option C"
      },
      {
        "label": "D",
        "text": "Option D"
      }
    ],
    "correctAnswer": "A",
    "explanation": "Detailed explanation for ela.revising.style.sentence_combining",
    "commonMistakes": [
      {
        "label": "Common error",
        "explanation": "Students often make this type of mistake."
      },
      {
        "label": "Another mistake",
        "explanation": "This is another frequent error."
      }
    ],
    "skills": [
      "sentence_combining"
    ],
    "tags": [
      "ela",
      "practice"
    ]
  },
  {
    "section": "ela",
    "category": "ela.revising.style.integrating_quotations",
    "difficulty": 1,
    "type": "multiple_choice",
    "stem": "Practice question 1 for integrating quotations",
    "options": [
      {
        "label": "A",
        "text": "Option A"
      },
      {
        "label": "B",
        "text": "Option B"
      },
      {
        "label": "C",
        "text": "Option C"
      },
      {
        "label": "D",
        "text": "Option D"
      }
    ],
    "correctAnswer": "A",
    "explanation": "Detailed explanation for ela.revising.style.integrating_quotations",
    "commonMistakes": [
      {
        "label": "Common error",
        "explanation": "Students often make this type of mistake."
      },
      {
        "label": "Another mistake",
        "explanation": "This is another frequent error."
      }
    ],
    "skills": [
      "integrating_quotations"
    ],
    "tags": [
      "ela",
      "practice"
    ]
  },
  {
    "section": "ela",
    "category": "ela.revising.style.integrating_quotations",
    "difficulty": 2,
    "type": "multiple_choice",
    "stem": "Practice question 2 for integrating quotations",
    "options": [
      {
        "label": "A",
        "text": "Option A"
      },
      {
        "label": "B",
        "text": "Option B"
      },
      {
        "label": "C",
        "text": "Option C"
      },
      {
        "label": "D",
        "text": "Option D"
      }
    ],
    "correctAnswer": "A",
    "explanation": "Detailed explanation for ela.revising.style.integrating_quotations",
    "commonMistakes": [
      {
        "label": "Common error",
        "explanation": "Students often make this type of mistake."
      },
      {
        "label": "Another mistake",
        "explanation": "This is another frequent error."
      }
    ],
    "skills": [
      "integrating_quotations"
    ],
    "tags": [
      "ela",
      "practice"
    ]
  },
  {
    "section": "ela",
    "category": "ela.revising.style.integrating_quotations",
    "difficulty": 3,
    "type": "multiple_choice",
    "stem": "Practice question 3 for integrating quotations",
    "options": [
      {
        "label": "A",
        "text": "Option A"
      },
      {
        "label": "B",
        "text": "Option B"
      },
      {
        "label": "C",
        "text": "Option C"
      },
      {
        "label": "D",
        "text": "Option D"
      }
    ],
    "correctAnswer": "A",
    "explanation": "Detailed explanation for ela.revising.style.integrating_quotations",
    "commonMistakes": [
      {
        "label": "Common error",
        "explanation": "Students often make this type of mistake."
      },
      {
        "label": "Another mistake",
        "explanation": "This is another frequent error."
      }
    ],
    "skills": [
      "integrating_quotations"
    ],
    "tags": [
      "ela",
      "practice"
    ]
  },
  {
    "section": "ela",
    "category": "ela.revising.style.integrating_quotations",
    "difficulty": 4,
    "type": "multiple_choice",
    "stem": "Practice question 4 for integrating quotations",
    "options": [
      {
        "label": "A",
        "text": "Option A"
      },
      {
        "label": "B",
        "text": "Option B"
      },
      {
        "label": "C",
        "text": "Option C"
      },
      {
        "label": "D",
        "text": "Option D"
      }
    ],
    "correctAnswer": "A",
    "explanation": "Detailed explanation for ela.revising.style.integrating_quotations",
    "commonMistakes": [
      {
        "label": "Common error",
        "explanation": "Students often make this type of mistake."
      },
      {
        "label": "Another mistake",
        "explanation": "This is another frequent error."
      }
    ],
    "skills": [
      "integrating_quotations"
    ],
    "tags": [
      "ela",
      "practice"
    ]
  },
  {
    "section": "ela",
    "category": "ela.revising.style.integrating_quotations",
    "difficulty": 5,
    "type": "multiple_choice",
    "stem": "Practice question 5 for integrating quotations",
    "options": [
      {
        "label": "A",
        "text": "Option A"
      },
      {
        "label": "B",
        "text": "Option B"
      },
      {
        "label": "C",
        "text": "Option C"
      },
      {
        "label": "D",
        "text": "Option D"
      }
    ],
    "correctAnswer": "A",
    "explanation": "Detailed explanation for ela.revising.style.integrating_quotations",
    "commonMistakes": [
      {
        "label": "Common error",
        "explanation": "Students often make this type of mistake."
      },
      {
        "label": "Another mistake",
        "explanation": "This is another frequent error."
      }
    ],
    "skills": [
      "integrating_quotations"
    ],
    "tags": [
      "ela",
      "practice"
    ]
  },
  {
    "section": "ela",
    "category": "ela.revising.style.integrating_quotations",
    "difficulty": 1,
    "type": "multiple_choice",
    "stem": "Practice question 6 for integrating quotations",
    "options": [
      {
        "label": "A",
        "text": "Option A"
      },
      {
        "label": "B",
        "text": "Option B"
      },
      {
        "label": "C",
        "text": "Option C"
      },
      {
        "label": "D",
        "text": "Option D"
      }
    ],
    "correctAnswer": "A",
    "explanation": "Detailed explanation for ela.revising.style.integrating_quotations",
    "commonMistakes": [
      {
        "label": "Common error",
        "explanation": "Students often make this type of mistake."
      },
      {
        "label": "Another mistake",
        "explanation": "This is another frequent error."
      }
    ],
    "skills": [
      "integrating_quotations"
    ],
    "tags": [
      "ela",
      "practice"
    ]
  },
  {
    "section": "ela",
    "category": "ela.revising.style.integrating_quotations",
    "difficulty": 2,
    "type": "multiple_choice",
    "stem": "Practice question 7 for integrating quotations",
    "options": [
      {
        "label": "A",
        "text": "Option A"
      },
      {
        "label": "B",
        "text": "Option B"
      },
      {
        "label": "C",
        "text": "Option C"
      },
      {
        "label": "D",
        "text": "Option D"
      }
    ],
    "correctAnswer": "A",
    "explanation": "Detailed explanation for ela.revising.style.integrating_quotations",
    "commonMistakes": [
      {
        "label": "Common error",
        "explanation": "Students often make this type of mistake."
      },
      {
        "label": "Another mistake",
        "explanation": "This is another frequent error."
      }
    ],
    "skills": [
      "integrating_quotations"
    ],
    "tags": [
      "ela",
      "practice"
    ]
  },
  {
    "section": "ela",
    "category": "ela.revising.style.integrating_quotations",
    "difficulty": 3,
    "type": "multiple_choice",
    "stem": "Practice question 8 for integrating quotations",
    "options": [
      {
        "label": "A",
        "text": "Option A"
      },
      {
        "label": "B",
        "text": "Option B"
      },
      {
        "label": "C",
        "text": "Option C"
      },
      {
        "label": "D",
        "text": "Option D"
      }
    ],
    "correctAnswer": "A",
    "explanation": "Detailed explanation for ela.revising.style.integrating_quotations",
    "commonMistakes": [
      {
        "label": "Common error",
        "explanation": "Students often make this type of mistake."
      },
      {
        "label": "Another mistake",
        "explanation": "This is another frequent error."
      }
    ],
    "skills": [
      "integrating_quotations"
    ],
    "tags": [
      "ela",
      "practice"
    ]
  },
  {
    "section": "ela",
    "category": "ela.revising.style.integrating_quotations",
    "difficulty": 4,
    "type": "multiple_choice",
    "stem": "Practice question 9 for integrating quotations",
    "options": [
      {
        "label": "A",
        "text": "Option A"
      },
      {
        "label": "B",
        "text": "Option B"
      },
      {
        "label": "C",
        "text": "Option C"
      },
      {
        "label": "D",
        "text": "Option D"
      }
    ],
    "correctAnswer": "A",
    "explanation": "Detailed explanation for ela.revising.style.integrating_quotations",
    "commonMistakes": [
      {
        "label": "Common error",
        "explanation": "Students often make this type of mistake."
      },
      {
        "label": "Another mistake",
        "explanation": "This is another frequent error."
      }
    ],
    "skills": [
      "integrating_quotations"
    ],
    "tags": [
      "ela",
      "practice"
    ]
  },
  {
    "section": "ela",
    "category": "ela.revising.style.integrating_quotations",
    "difficulty": 5,
    "type": "multiple_choice",
    "stem": "Practice question 10 for integrating quotations",
    "options": [
      {
        "label": "A",
        "text": "Option A"
      },
      {
        "label": "B",
        "text": "Option B"
      },
      {
        "label": "C",
        "text": "Option C"
      },
      {
        "label": "D",
        "text": "Option D"
      }
    ],
    "correctAnswer": "A",
    "explanation": "Detailed explanation for ela.revising.style.integrating_quotations",
    "commonMistakes": [
      {
        "label": "Common error",
        "explanation": "Students often make this type of mistake."
      },
      {
        "label": "Another mistake",
        "explanation": "This is another frequent error."
      }
    ],
    "skills": [
      "integrating_quotations"
    ],
    "tags": [
      "ela",
      "practice"
    ]
  }
]